huaweicloudsdktics/__init__.py
huaweicloudsdktics/v1/__init__.py
huaweicloudsdktics/v1/tics_async_client.py
huaweicloudsdktics/v1/tics_client.py
huaweicloudsdktics/v1/model/__init__.py
huaweicloudsdktics/v1/model/agent_list_vo.py
huaweicloudsdktics/v1/model/deploy_vo.py
huaweicloudsdktics/v1/model/fl_job_list_vo.py
huaweicloudsdktics/v1/model/job_report_base_info_vo.py
huaweicloudsdktics/v1/model/job_report_env_vo.py
huaweicloudsdktics/v1/model/job_report_output_vo.py
huaweicloudsdktics/v1/model/job_report_partner_vo.py
huaweicloudsdktics/v1/model/league_dataset_statistics_vo.py
huaweicloudsdktics/v1/model/league_partner_statistics_vo.py
huaweicloudsdktics/v1/model/league_update_vo.py
huaweicloudsdktics/v1/model/list_agents_request.py
huaweicloudsdktics/v1/model/list_agents_response.py
huaweicloudsdktics/v1/model/list_audit_info_request.py
huaweicloudsdktics/v1/model/list_audit_info_response.py
huaweicloudsdktics/v1/model/list_fl_job_request.py
huaweicloudsdktics/v1/model/list_fl_job_response.py
huaweicloudsdktics/v1/model/list_instance_history_request.py
huaweicloudsdktics/v1/model/list_instance_history_response.py
huaweicloudsdktics/v1/model/list_league_datasets_request.py
huaweicloudsdktics/v1/model/list_league_datasets_response.py
huaweicloudsdktics/v1/model/list_leagues_request.py
huaweicloudsdktics/v1/model/list_leagues_response.py
huaweicloudsdktics/v1/model/list_nodes_request.py
huaweicloudsdktics/v1/model/list_nodes_response.py
huaweicloudsdktics/v1/model/list_notices_request.py
huaweicloudsdktics/v1/model/list_notices_response.py
huaweicloudsdktics/v1/model/list_partners_request.py
huaweicloudsdktics/v1/model/list_partners_response.py
huaweicloudsdktics/v1/model/list_sql_job_request.py
huaweicloudsdktics/v1/model/list_sql_job_response.py
huaweicloudsdktics/v1/model/partner_data_vo.py
huaweicloudsdktics/v1/model/processor_vo.py
huaweicloudsdktics/v1/model/round_deploy_vo.py
huaweicloudsdktics/v1/model/show_agent_detail_request.py
huaweicloudsdktics-3.1.184.dist-info/METADATA
huaweicloudsdktics-3.1.184.dist-info/WHEEL
huaweicloudsdktics-3.1.184.dist-info/licenses/LICENSE
huaweicloudsdktics-3.1.184.dist-info/RECORD
